pyams_gis/__init__.py
pyams_gis/area.py
pyams_gis/configuration.py
pyams_gis/include.py
pyams_gis/layer.py
pyams_gis/point.py
pyams_gis/schema.py
pyams_gis/transform.py
pyams_gis/utility.py
pyams_gis/api/__init__.py
pyams_gis/api/schema.py
pyams_gis/doctests/README.rst
pyams_gis/generations/__init__.py
pyams_gis/interfaces/__init__.py
pyams_gis/interfaces/configuration.py
pyams_gis/interfaces/layer.py
pyams_gis/interfaces/utility.py
pyams_gis/interfaces/widget.py
pyams_gis/interfaces/templates/geoarea-input.pt
pyams_gis/interfaces/templates/geopoint-input.pt
pyams_gis/locales/pyams_gis.pot
pyams_gis/locales/fr/LC_MESSAGES/pyams_gis.mo
pyams_gis/locales/fr/LC_MESSAGES/pyams_gis.po
pyams_gis/resources/css/Control.FullScreen.css
pyams_gis/resources/css/Control.FullScreen.min.css
pyams_gis/resources/css/GpPluginLeaflet.css
pyams_gis/resources/css/GpPluginLeaflet.min.css
pyams_gis/resources/css/MarkerCluster.css
pyams_gis/resources/css/MarkerCluster.min.css
pyams_gis/resources/css/icon-fullscreen.svg
pyams_gis/resources/css/leaflet-1.9.4.css
pyams_gis/resources/css/leaflet-1.9.4.min.css
pyams_gis/resources/css/leaflet-draw.css
pyams_gis/resources/css/leaflet-gesture-handling.css
pyams_gis/resources/css/leaflet-gesture-handling.min.css
pyams_gis/resources/css/images/layers.png
pyams_gis/resources/css/images/marker-icon-2x.png
pyams_gis/resources/css/images/marker-icon.png
pyams_gis/resources/css/images/marker-shadow.png
pyams_gis/resources/img/fullscreen.png
pyams_gis/resources/img/fullscreen@2x.png
pyams_gis/resources/img/layers-2x.png
pyams_gis/resources/img/marker-icon-2x.png
pyams_gis/resources/img/marker-icon.png
pyams_gis/resources/img/marker-shadow.png
pyams_gis/resources/img/spritesheet-2x.png
pyams_gis/resources/img/spritesheet.png
pyams_gis/resources/img/spritesheet.svg
pyams_gis/resources/img/esri/loading.gif
pyams_gis/resources/img/esri/loading@2x.gif
pyams_gis/resources/img/esri/search-disabled.png
pyams_gis/resources/img/esri/search.png
pyams_gis-2.1.3.dist-info/LICENSE
pyams_gis-2.1.3.dist-info/METADATA
pyams_gis-2.1.3.dist-info/WHEEL
pyams_gis-2.1.3.dist-info/entry_points.txt
pyams_gis-2.1.3.dist-info/namespace_packages.txt
pyams_gis-2.1.3.dist-info/top_level.txt
pyams_gis-2.1.3.dist-info/RECORD
